{
    "key": "group_5e337c6f1ba65",
    "title": "Blocks",
    "fields": [
        {
            "key": "field_5e337c7407471",
            "label": "Blocks",
            "name": "blocks",
            "type": "flexible_content",
            "instructions": "",
            "required": 0,
            "conditional_logic": 0,
            "wrapper": {
                "width": "",
                "class": "",
                "id": ""
            },
            "layouts": {
                "layout_5e3396eb3c452": {
                    "key": "layout_5e3396eb3c452",
                    "name": "fullwidth_text",
                    "label": "Fullwidth Text",
                    "display": "block",
                    "sub_fields": [
                        {
                            "key": "field_61b27c82163b1",
                            "label": "Text",
                            "name": "text",
                            "type": "wysiwyg",
                            "instructions": "",
                            "required": 0,
                            "conditional_logic": 0,
                            "wrapper": {
                                "width": "",
                                "class": "",
                                "id": ""
                            },
                            "tabs": "all",
                            "toolbar": "full",
                            "media_upload": 1,
                            "default_value": "",
                            "delay": 0
                        }
                    ],
                    "min": "",
                    "max": ""
                },
                "layout_61b78681e275e": {
                    "key": "layout_61b78681e275e",
                    "name": "faq_block",
                    "label": "Faq Block",
                    "display": "block",
                    "sub_fields": [
                        {
                            "key": "field_61b7868fe275f",
                            "label": "fields",
                            "name": "fields",
                            "type": "clone",
                            "instructions": "",
                            "required": 0,
                            "conditional_logic": 0,
                            "wrapper": {
                                "width": "",
                                "class": "",
                                "id": ""
                            },
                            "clone": [
                                "group_61b7859955301"
                            ],
                            "display": "seamless",
                            "layout": "block",
                            "prefix_label": 0,
                            "prefix_name": 0
                        }
                    ],
                    "min": "",
                    "max": ""
                },
                "layout_61b7c71c4964d": {
                    "key": "layout_61b7c71c4964d",
                    "name": "about_block",
                    "label": "About Block",
                    "display": "block",
                    "sub_fields": [
                        {
                            "key": "field_61b7c7304964e",
                            "label": "About Field",
                            "name": "about_field",
                            "type": "clone",
                            "instructions": "",
                            "required": 0,
                            "conditional_logic": 0,
                            "wrapper": {
                                "width": "",
                                "class": "",
                                "id": ""
                            },
                            "clone": [
                                "group_61b7c669423f1"
                            ],
                            "display": "seamless",
                            "layout": "block",
                            "prefix_label": 0,
                            "prefix_name": 0
                        }
                    ],
                    "min": "",
                    "max": ""
                },
                "layout_61b7dffdd6498": {
                    "key": "layout_61b7dffdd6498",
                    "name": "affiliat",
                    "label": "Affiliat",
                    "display": "block",
                    "sub_fields": [
                        {
                            "key": "field_61b7e005d6499",
                            "label": "Affiliat",
                            "name": "affiliat",
                            "type": "clone",
                            "instructions": "",
                            "required": 0,
                            "conditional_logic": 0,
                            "wrapper": {
                                "width": "",
                                "class": "",
                                "id": ""
                            },
                            "clone": [
                                "group_61b7dead60c2a"
                            ],
                            "display": "seamless",
                            "layout": "block",
                            "prefix_label": 0,
                            "prefix_name": 0
                        }
                    ],
                    "min": "",
                    "max": ""
                },
                "layout_61b7ea403350b": {
                    "key": "layout_61b7ea403350b",
                    "name": "contact_us",
                    "label": "Contact Us",
                    "display": "block",
                    "sub_fields": [
                        {
                            "key": "field_61b7ea493350c",
                            "label": "Contact Us",
                            "name": "contact_us_block",
                            "type": "clone",
                            "instructions": "",
                            "required": 0,
                            "conditional_logic": 0,
                            "wrapper": {
                                "width": "",
                                "class": "",
                                "id": ""
                            },
                            "clone": [
                                "group_61b7e845c401c"
                            ],
                            "display": "seamless",
                            "layout": "block",
                            "prefix_label": 0,
                            "prefix_name": 0
                        }
                    ],
                    "min": "",
                    "max": ""
                },
                "layout_61ba5dac02739": {
                    "key": "layout_61ba5dac02739",
                    "name": "home_slider",
                    "label": "Home Slider",
                    "display": "block",
                    "sub_fields": [
                        {
                            "key": "field_61ba5db10273a",
                            "label": "fields",
                            "name": "fields",
                            "type": "clone",
                            "instructions": "",
                            "required": 0,
                            "conditional_logic": 0,
                            "wrapper": {
                                "width": "",
                                "class": "",
                                "id": ""
                            },
                            "clone": [
                                "group_61b8f98fb1933"
                            ],
                            "display": "seamless",
                            "layout": "block",
                            "prefix_label": 0,
                            "prefix_name": 0
                        }
                    ],
                    "min": "",
                    "max": ""
                },
                "layout_61ba5dd20273b": {
                    "key": "layout_61ba5dd20273b",
                    "name": "subscription_block",
                    "label": "Subscription Block",
                    "display": "block",
                    "sub_fields": [
                        {
                            "key": "field_61ba5ddc0273c",
                            "label": "Subscription Block",
                            "name": "subscription_block",
                            "type": "clone",
                            "instructions": "",
                            "required": 0,
                            "conditional_logic": 0,
                            "wrapper": {
                                "width": "",
                                "class": "",
                                "id": ""
                            },
                            "clone": [
                                "group_61b90df8ddcd1"
                            ],
                            "display": "seamless",
                            "layout": "block",
                            "prefix_label": 0,
                            "prefix_name": 0
                        }
                    ],
                    "min": "",
                    "max": ""
                },
                "layout_61ba5e200273d": {
                    "key": "layout_61ba5e200273d",
                    "name": "feature_brand_block",
                    "label": "Feature Brand Block",
                    "display": "block",
                    "sub_fields": [
                        {
                            "key": "field_61ba5e2c0273e",
                            "label": "Feature Brand Block",
                            "name": "feature_brand_block",
                            "type": "clone",
                            "instructions": "",
                            "required": 0,
                            "conditional_logic": 0,
                            "wrapper": {
                                "width": "",
                                "class": "",
                                "id": ""
                            },
                            "clone": [
                                "group_61b917a0e92b0"
                            ],
                            "display": "seamless",
                            "layout": "block",
                            "prefix_label": 0,
                            "prefix_name": 0
                        }
                    ],
                    "min": "",
                    "max": ""
                },
                "layout_61ba5e4f0273f": {
                    "key": "layout_61ba5e4f0273f",
                    "name": "featured_product_block",
                    "label": "Featured Product Block",
                    "display": "block",
                    "sub_fields": [
                        {
                            "key": "field_61ba5e5b02740",
                            "label": "Featured Product Block",
                            "name": "featured_product_block",
                            "type": "clone",
                            "instructions": "",
                            "required": 0,
                            "conditional_logic": 0,
                            "wrapper": {
                                "width": "",
                                "class": "",
                                "id": ""
                            },
                            "clone": [
                                "group_61b91d059282e"
                            ],
                            "display": "seamless",
                            "layout": "block",
                            "prefix_label": 0,
                            "prefix_name": 0
                        }
                    ],
                    "min": "",
                    "max": ""
                },
                "layout_61cb5670d326b": {
                    "key": "layout_61cb5670d326b",
                    "name": "request_quote",
                    "label": "Request Quote ",
                    "display": "block",
                    "sub_fields": [
                        {
                            "key": "field_61cb5689d326c",
                            "label": "fields",
                            "name": "fields",
                            "type": "clone",
                            "instructions": "",
                            "required": 0,
                            "conditional_logic": 0,
                            "wrapper": {
                                "width": "",
                                "class": "",
                                "id": ""
                            },
                            "clone": [
                                "group_61cb541bccb64"
                            ],
                            "display": "seamless",
                            "layout": "block",
                            "prefix_label": 0,
                            "prefix_name": 0
                        }
                    ],
                    "min": "",
                    "max": ""
                },
                "layout_61cbb1da9de76": {
                    "key": "layout_61cbb1da9de76",
                    "name": "order_tracking",
                    "label": "Order Tracking",
                    "display": "block",
                    "sub_fields": [
                        {
                            "key": "field_61cbb1ef9de77",
                            "label": "Order Track Field",
                            "name": "order_track_field",
                            "type": "clone",
                            "instructions": "",
                            "required": 0,
                            "conditional_logic": 0,
                            "wrapper": {
                                "width": "",
                                "class": "",
                                "id": ""
                            },
                            "clone": [
                                "group_61cbb15704472"
                            ],
                            "display": "seamless",
                            "layout": "block",
                            "prefix_label": 0,
                            "prefix_name": 0
                        }
                    ],
                    "min": "",
                    "max": ""
                },
                "layout_61e866297cd95": {
                    "key": "layout_61e866297cd95",
                    "name": "brand_product",
                    "label": "Brand Product",
                    "display": "block",
                    "sub_fields": [
                        {
                            "key": "field_61e866347cd96",
                            "label": "Brand Product Field",
                            "name": "brand_product_field",
                            "type": "clone",
                            "instructions": "",
                            "required": 0,
                            "conditional_logic": 0,
                            "wrapper": {
                                "width": "",
                                "class": "",
                                "id": ""
                            },
                            "clone": [
                                "group_61e7585f53658"
                            ],
                            "display": "seamless",
                            "layout": "block",
                            "prefix_label": 0,
                            "prefix_name": 0
                        }
                    ],
                    "min": "",
                    "max": ""
                }
            },
            "button_label": "Add Block",
            "min": "",
            "max": ""
        }
    ],
    "location": [
        [
            {
                "param": "post_type",
                "operator": "==",
                "value": "page"
            }
        ],
        [
            {
                "param": "post_type",
                "operator": "==",
                "value": "globalblock"
            }
        ]
    ],
    "menu_order": 10,
    "position": "acf_after_title",
    "style": "seamless",
    "label_placement": "top",
    "instruction_placement": "label",
    "hide_on_screen": [
        "the_content",
        "discussion",
        "comments"
    ],
    "active": true,
    "description": "Block Chooser for all content types that will have blocks.",
    "modified": 1642718782
}